{
  "festival": "Le Chien à Plumes",
  "shortName": "Le Chien à Plumes",
  "location": "Villegusien-le-Lac",
  "timezone": "Europe/Paris",
  "color": "#6E6E6E",
  "source": "https://www.chienaplumes.fr — têtes d'affiche annoncées par jour, horaires/scènes non publiés (extraction 2026-06-10)",
  "status": "Running Order Incomplet",
  "warning": "Running order incomplet — line-up partiel annoncé, horaires non publiés",
  "stages": [],
  "days": [
    {
      "id": 1,
      "label": "Vendredi 31",
      "date": "2026-07-31"
    },
    {
      "id": 2,
      "label": "Samedi 1",
      "date": "2026-08-01"
    },
    {
      "id": 3,
      "label": "Dimanche 2",
      "date": "2026-08-02"
    }
  ],
  "concerts": [
    {
      "id": "d1-na-deluxe",
      "artist": "Deluxe (carte blanche)",
      "stage": null,
      "festivalDay": 1,
      "start": null,
      "end": null,
      "appleMusicPlaylist": null,
      "appleMusicArtistId": null,
      "musicBrainzId": null,
      "spotifyArtistId": null,
      "deezerArtistId": null,
      "instagramHandle": null
    },
    {
      "id": "d1-na-suzane",
      "artist": "Suzane",
      "stage": null,
      "festivalDay": 1,
      "start": null,
      "end": null,
      "appleMusicPlaylist": null,
      "appleMusicArtistId": null,
      "musicBrainzId": null,
      "spotifyArtistId": null,
      "deezerArtistId": null,
      "instagramHandle": null,
      "description": "Océane Colom, dite Suzane, née le 29 décembre 1990 à Avignon, est une autrice-compositrice-interprète française."
    },
    {
      "id": "d2-na-dub-inc",
      "artist": "Dub Inc",
      "stage": null,
      "festivalDay": 2,
      "start": null,
      "end": null,
      "appleMusicPlaylist": null,
      "appleMusicArtistId": null,
      "musicBrainzId": null,
      "spotifyArtistId": null,
      "deezerArtistId": null,
      "instagramHandle": null,
      "description": "Dub Inc, anciennement Dub Incorporation, est un groupe français de reggae, originaire de Saint-Étienne, dans la Loire."
    },
    {
      "id": "d2-na-yame",
      "artist": "Yamê",
      "stage": null,
      "festivalDay": 2,
      "start": null,
      "end": null,
      "appleMusicPlaylist": null,
      "appleMusicArtistId": null,
      "musicBrainzId": null,
      "spotifyArtistId": null,
      "deezerArtistId": null,
      "instagramHandle": null,
      "description": "Emmanuel Sow, connu sous son nom de scène Yamê, né le 19 avril 1993 à Cergy-Pontoise (Val-d'Oise), est un chanteur et rappeur franco-camerounais."
    },
    {
      "id": "d3-na-louis-bertignac",
      "artist": "Louis Bertignac",
      "stage": null,
      "festivalDay": 3,
      "start": null,
      "end": null,
      "appleMusicPlaylist": null,
      "appleMusicArtistId": null,
      "musicBrainzId": null,
      "spotifyArtistId": null,
      "deezerArtistId": null,
      "instagramHandle": null,
      "description": "Louis Bertignac, né le 23 février 1954 à Oran, est un musicien français, parolier, chanteur, guitariste et cofondateur du groupe de rock français Téléphone, avec lequel il a vendu près de six millions de disques."
    },
    {
      "id": "d3-na-fatoumata-diawara",
      "artist": "Fatoumata Diawara",
      "stage": null,
      "festivalDay": 3,
      "start": null,
      "end": null,
      "appleMusicPlaylist": null,
      "appleMusicArtistId": null,
      "musicBrainzId": null,
      "spotifyArtistId": null,
      "deezerArtistId": null,
      "instagramHandle": null,
      "description": "Fatoumata Diawara, née le 21 février 1982 à Abidjan de parents maliens, est une chanteuse, comédienne et auteure-compositrice-interprète malienne. Elle vit entre Bamako et Milan."
    }
  ]
}