{
  "festival": "Musicalarue",
  "shortName": "Musicalarue",
  "location": "Luxey",
  "timezone": "Europe/Paris",
  "color": "#6E6E6E",
  "source": "https://www.musicalarue.com/le-festival/ (statut : Running Order Incomplet — line-up annoncé par jour, horaires et scènes non publiés ; extraction 2026-06-10)",
  "status": "Running Order Incomplet",
  "warning": "Running order incomplet — line-up annoncé par jour, horaires non publiés et scènes non assignées",
  "stages": [],
  "days": [
    {
      "id": 1,
      "label": "Vendredi 31",
      "date": "2026-07-31"
    },
    {
      "id": 2,
      "label": "Samedi 1",
      "date": "2026-08-01"
    },
    {
      "id": 3,
      "label": "Dimanche 2",
      "date": "2026-08-02"
    }
  ],
  "concerts": [
    {
      "id": "d1-na-jean-louis-aubert",
      "artist": "Jean-Louis Aubert",
      "stage": null,
      "festivalDay": 1,
      "start": null,
      "end": null,
      "appleMusicPlaylist": null,
      "appleMusicArtistId": null,
      "musicBrainzId": null,
      "spotifyArtistId": null,
      "deezerArtistId": null,
      "instagramHandle": null,
      "description": "Jean-Louis Aubert, né le 12 avril 1955 à Nantua (Ain), est un auteur-compositeur-interprète, chanteur, guitariste et producteur français, artiste de rock avec le groupe Téléphone, puis en solo et à partir de 2015 en…"
    },
    {
      "id": "d1-na-keny-arkana",
      "artist": "Keny Arkana",
      "stage": null,
      "festivalDay": 1,
      "start": null,
      "end": null,
      "appleMusicPlaylist": null,
      "appleMusicArtistId": null,
      "musicBrainzId": null,
      "spotifyArtistId": null,
      "deezerArtistId": null,
      "instagramHandle": null,
      "description": "Keny Arkana, née le 20 décembre 1982 à Boulogne-Billancourt, est une rappeuse française d'origine franco-argentine originaire de Marseille dans les Bouches-du-Rhône."
    },
    {
      "id": "d1-na-gael-faye",
      "artist": "Gaël Faye",
      "stage": null,
      "festivalDay": 1,
      "start": null,
      "end": null,
      "appleMusicPlaylist": null,
      "appleMusicArtistId": null,
      "musicBrainzId": null,
      "spotifyArtistId": null,
      "deezerArtistId": null,
      "instagramHandle": null,
      "description": "Gaël Faye, né le 6 août 1982 à Bujumbura (Burundi), est un rappeur, chanteur, auteur-compositeur-interprète et écrivain franco-rwandais."
    },
    {
      "id": "d1-na-gramatik",
      "artist": "Gramatik",
      "stage": null,
      "festivalDay": 1,
      "start": null,
      "end": null,
      "appleMusicPlaylist": null,
      "appleMusicArtistId": null,
      "musicBrainzId": null,
      "spotifyArtistId": null,
      "deezerArtistId": null,
      "instagramHandle": null,
      "description": "Gramatik, de son vrai nom Denis Jašarević, est un DJ, producteur slovène, né le 19 octobre 1984 à Portorož, Slovénie."
    },
    {
      "id": "d1-na-sam-sauvage",
      "artist": "Sam Sauvage",
      "stage": null,
      "festivalDay": 1,
      "start": null,
      "end": null,
      "appleMusicPlaylist": null,
      "appleMusicArtistId": null,
      "musicBrainzId": null,
      "spotifyArtistId": null,
      "deezerArtistId": null,
      "instagramHandle": null,
      "description": "Hugo Brebion dit Sam Sauvage, né le 25 avril 2000 à Saint-Martin-Boulogne (Pas-de-Calais), est un auteur-compositeur-interprète français."
    },
    {
      "id": "d1-na-dub-pistols",
      "artist": "Dub Pistols",
      "stage": null,
      "festivalDay": 1,
      "start": null,
      "end": null,
      "appleMusicPlaylist": null,
      "appleMusicArtistId": null,
      "musicBrainzId": null,
      "spotifyArtistId": null,
      "deezerArtistId": null,
      "instagramHandle": null,
      "description": "Dub Pistols est un groupe de dub/big beat londonien fondé en 1996 grâce à Barry Ashworth. Celui-ci rencontrera John King (guitariste), Jason O'Bryan (bassiste), T.K."
    },
    {
      "id": "d1-na-dope-saint-jude",
      "artist": "Dope Saint Jude",
      "stage": null,
      "festivalDay": 1,
      "start": null,
      "end": null,
      "appleMusicPlaylist": null,
      "appleMusicArtistId": null,
      "musicBrainzId": null,
      "spotifyArtistId": null,
      "deezerArtistId": null,
      "instagramHandle": null,
      "description": "Catherine Saint Jude Pretorius, connue sous le pseudo de Dope Saint Jude, est une rappeuse, chanteuse, auteure-compositrice et productrice de musique sud-africaine."
    },
    {
      "id": "d1-na-mpl",
      "artist": "MPL",
      "stage": null,
      "festivalDay": 1,
      "start": null,
      "end": null,
      "appleMusicPlaylist": null,
      "appleMusicArtistId": null,
      "musicBrainzId": null,
      "spotifyArtistId": null,
      "deezerArtistId": null,
      "instagramHandle": null
    },
    {
      "id": "d1-na-thibault-cauvin",
      "artist": "Thibault Cauvin",
      "stage": null,
      "festivalDay": 1,
      "start": null,
      "end": null,
      "appleMusicPlaylist": null,
      "appleMusicArtistId": null,
      "musicBrainzId": null,
      "spotifyArtistId": null,
      "deezerArtistId": null,
      "instagramHandle": null,
      "description": "Thibault Cauvin est un guitariste français, né le 16 juillet 1984 à Bordeaux. Il est l'un des guitaristes les plus récompensés au monde avec 36 prix internationaux."
    },
    {
      "id": "d1-na-les-croquants",
      "artist": "Les Croquants",
      "stage": null,
      "festivalDay": 1,
      "start": null,
      "end": null,
      "appleMusicPlaylist": null,
      "appleMusicArtistId": null,
      "musicBrainzId": null,
      "spotifyArtistId": null,
      "deezerArtistId": null,
      "instagramHandle": null,
      "description": "Les Croquants est un groupe de folk français, formé par Danito et M. Kif,"
    },
    {
      "id": "d1-na-joe-yorke",
      "artist": "Joe Yorke",
      "stage": null,
      "festivalDay": 1,
      "start": null,
      "end": null,
      "appleMusicPlaylist": null,
      "appleMusicArtistId": null,
      "musicBrainzId": null,
      "spotifyArtistId": null,
      "deezerArtistId": null,
      "instagramHandle": null,
      "description": "Ashton Donald Joseph « Joe » Yorke, né le 7 décembre 1947 à Wanganui, est une cavalier néo-zélandais de saut d'obstacles."
    },
    {
      "id": "d1-na-bardix-le-gaulois",
      "artist": "Bardix le Gaulois",
      "stage": null,
      "festivalDay": 1,
      "start": null,
      "end": null,
      "appleMusicPlaylist": null,
      "appleMusicArtistId": null,
      "musicBrainzId": null,
      "spotifyArtistId": null,
      "deezerArtistId": null,
      "instagramHandle": null
    },
    {
      "id": "d1-na-les-hurlements-d-leo",
      "artist": "Les Hurlements d'Léo",
      "stage": null,
      "festivalDay": 1,
      "start": null,
      "end": null,
      "appleMusicPlaylist": null,
      "appleMusicArtistId": null,
      "musicBrainzId": null,
      "spotifyArtistId": null,
      "deezerArtistId": null,
      "instagramHandle": null,
      "description": "Les Hurlements d'Léo, parfois abrégé en HDL, est un groupe de rock français, originaire de Bordeaux, Gironde. Ils jouent un genre qu'ils définissent eux-mêmes en plaisantant comme « java-chanson-punk-caravaning »."
    },
    {
      "id": "d1-na-pussy-miel",
      "artist": "Pussy Miel",
      "stage": null,
      "festivalDay": 1,
      "start": null,
      "end": null,
      "appleMusicPlaylist": null,
      "appleMusicArtistId": null,
      "musicBrainzId": null,
      "spotifyArtistId": null,
      "deezerArtistId": null,
      "instagramHandle": null
    },
    {
      "id": "d1-na-marcia",
      "artist": "Marcia",
      "stage": null,
      "festivalDay": 1,
      "start": null,
      "end": null,
      "appleMusicPlaylist": null,
      "appleMusicArtistId": null,
      "musicBrainzId": null,
      "spotifyArtistId": null,
      "deezerArtistId": null,
      "instagramHandle": null,
      "description": "Marcia est l'épouse de Marcus Ulpius Traianus et la mère de l’empereur Trajan. Elle est peut-être aussi la demi-sœur aînée de Marcia Furnilla, la seconde épouse de Titus, et la tante de Julia Titi."
    },
    {
      "id": "d1-na-trab-terapy",
      "artist": "Trab Teräpy",
      "stage": null,
      "festivalDay": 1,
      "start": null,
      "end": null,
      "appleMusicPlaylist": null,
      "appleMusicArtistId": null,
      "musicBrainzId": null,
      "spotifyArtistId": null,
      "deezerArtistId": null,
      "instagramHandle": null
    },
    {
      "id": "d1-na-dj-set-groland",
      "artist": "DJ set Groland",
      "stage": null,
      "festivalDay": 1,
      "start": null,
      "end": null,
      "appleMusicPlaylist": null,
      "appleMusicArtistId": null,
      "musicBrainzId": null,
      "spotifyArtistId": null,
      "deezerArtistId": null,
      "instagramHandle": null
    },
    {
      "id": "d1-na-jasmine-not-jafar",
      "artist": "Jasmine Not Jafar",
      "stage": null,
      "festivalDay": 1,
      "start": null,
      "end": null,
      "appleMusicPlaylist": null,
      "appleMusicArtistId": null,
      "musicBrainzId": null,
      "spotifyArtistId": null,
      "deezerArtistId": null,
      "instagramHandle": null
    },
    {
      "id": "d1-na-violent-sadie-mode",
      "artist": "Violent Sadie Mode",
      "stage": null,
      "festivalDay": 1,
      "start": null,
      "end": null,
      "appleMusicPlaylist": null,
      "appleMusicArtistId": null,
      "musicBrainzId": null,
      "spotifyArtistId": null,
      "deezerArtistId": null,
      "instagramHandle": null
    },
    {
      "id": "d1-na-odeza",
      "artist": "Odeza",
      "stage": null,
      "festivalDay": 1,
      "start": null,
      "end": null,
      "appleMusicPlaylist": null,
      "appleMusicArtistId": null,
      "musicBrainzId": null,
      "spotifyArtistId": null,
      "deezerArtistId": null,
      "instagramHandle": null
    },
    {
      "id": "d2-na-ub40",
      "artist": "UB40",
      "stage": null,
      "festivalDay": 2,
      "start": null,
      "end": null,
      "appleMusicPlaylist": null,
      "appleMusicArtistId": null,
      "musicBrainzId": null,
      "spotifyArtistId": null,
      "deezerArtistId": null,
      "instagramHandle": null,
      "description": "UB40 est un groupe britannique de reggae fondé en 1978 à Birmingham (Angleterre)."
    },
    {
      "id": "d2-na-laurent-voulzy",
      "artist": "Laurent Voulzy",
      "stage": null,
      "festivalDay": 2,
      "start": null,
      "end": null,
      "appleMusicPlaylist": null,
      "appleMusicArtistId": null,
      "musicBrainzId": null,
      "spotifyArtistId": null,
      "deezerArtistId": null,
      "instagramHandle": null,
      "description": "Laurent Voulzy, est un chanteur, auteur-compositeur-interprète et guitariste français, né le 18 décembre 1948 dans le 18e arrondissement de Paris."
    },
    {
      "id": "d2-na-feu-chatterton",
      "artist": "Feu! Chatterton",
      "stage": null,
      "festivalDay": 2,
      "start": null,
      "end": null,
      "appleMusicPlaylist": null,
      "appleMusicArtistId": null,
      "musicBrainzId": null,
      "spotifyArtistId": null,
      "deezerArtistId": null,
      "instagramHandle": null,
      "description": "Feu! Chatterton est un groupe de pop-rock français, formé en 2011 à Paris."
    },
    {
      "id": "d2-na-miki",
      "artist": "Miki",
      "stage": null,
      "festivalDay": 2,
      "start": null,
      "end": null,
      "appleMusicPlaylist": null,
      "appleMusicArtistId": null,
      "musicBrainzId": null,
      "spotifyArtistId": null,
      "deezerArtistId": null,
      "instagramHandle": null
    },
    {
      "id": "d2-na-enhancer",
      "artist": "Enhancer",
      "stage": null,
      "festivalDay": 2,
      "start": null,
      "end": null,
      "appleMusicPlaylist": null,
      "appleMusicArtistId": null,
      "musicBrainzId": null,
      "spotifyArtistId": null,
      "deezerArtistId": null,
      "instagramHandle": null
    },
    {
      "id": "d2-na-youssoupha",
      "artist": "Youssoupha",
      "stage": null,
      "festivalDay": 2,
      "start": null,
      "end": null,
      "appleMusicPlaylist": null,
      "appleMusicArtistId": null,
      "musicBrainzId": null,
      "spotifyArtistId": null,
      "deezerArtistId": null,
      "instagramHandle": null,
      "description": "Youssoupha Mabiki, dit Youssoupha, né le 29 avril 1979 à Kinshasa au Zaïre, est un rappeur, chanteur, producteur et auteur-compositeur-interprète franco-congolais."
    },
    {
      "id": "d2-na-groundation",
      "artist": "Groundation",
      "stage": null,
      "festivalDay": 2,
      "start": null,
      "end": null,
      "appleMusicPlaylist": null,
      "appleMusicArtistId": null,
      "musicBrainzId": null,
      "spotifyArtistId": null,
      "deezerArtistId": null,
      "instagramHandle": null,
      "description": "Groundation est un groupe américain de roots reggae, originaire de Sonoma, en Californie du Nord. Il est souvent considéré comme un des groupes les plus emblématique de la scène reggae des années 2000."
    },
    {
      "id": "d2-na-tetes-raides",
      "artist": "Têtes Raides",
      "stage": null,
      "festivalDay": 2,
      "start": null,
      "end": null,
      "appleMusicPlaylist": null,
      "appleMusicArtistId": null,
      "musicBrainzId": null,
      "spotifyArtistId": null,
      "deezerArtistId": null,
      "instagramHandle": null,
      "description": "Têtes raides est un groupe de rock français, originaire de la banlieue parisienne, formé en 1984. Il mélange la musique de cirque moderne, la poésie, la peinture et le théâtre."
    },
    {
      "id": "d2-na-skarra-mucci-x-manudigital",
      "artist": "Skarra Mucci x Manudigital",
      "stage": null,
      "festivalDay": 2,
      "start": null,
      "end": null,
      "appleMusicPlaylist": null,
      "appleMusicArtistId": null,
      "musicBrainzId": null,
      "spotifyArtistId": null,
      "deezerArtistId": null,
      "instagramHandle": null
    },
    {
      "id": "d2-na-guiz-de-tryo",
      "artist": "Guiz (de Tryo)",
      "stage": null,
      "festivalDay": 2,
      "start": null,
      "end": null,
      "appleMusicPlaylist": null,
      "appleMusicArtistId": null,
      "musicBrainzId": null,
      "spotifyArtistId": null,
      "deezerArtistId": null,
      "instagramHandle": null
    },
    {
      "id": "d2-na-l-ultrabal",
      "artist": "L'Ultrabal",
      "stage": null,
      "festivalDay": 2,
      "start": null,
      "end": null,
      "appleMusicPlaylist": null,
      "appleMusicArtistId": null,
      "musicBrainzId": null,
      "spotifyArtistId": null,
      "deezerArtistId": null,
      "instagramHandle": null
    },
    {
      "id": "d2-na-oai-reggae-party",
      "artist": "OAI Reggae Party",
      "stage": null,
      "festivalDay": 2,
      "start": null,
      "end": null,
      "appleMusicPlaylist": null,
      "appleMusicArtistId": null,
      "musicBrainzId": null,
      "spotifyArtistId": null,
      "deezerArtistId": null,
      "instagramHandle": null
    },
    {
      "id": "d2-na-st-graal",
      "artist": "ST Graal",
      "stage": null,
      "festivalDay": 2,
      "start": null,
      "end": null,
      "appleMusicPlaylist": null,
      "appleMusicArtistId": null,
      "musicBrainzId": null,
      "spotifyArtistId": null,
      "deezerArtistId": null,
      "instagramHandle": null
    },
    {
      "id": "d2-na-dougy",
      "artist": "Dougy",
      "stage": null,
      "festivalDay": 2,
      "start": null,
      "end": null,
      "appleMusicPlaylist": null,
      "appleMusicArtistId": null,
      "musicBrainzId": null,
      "spotifyArtistId": null,
      "deezerArtistId": null,
      "instagramHandle": null
    },
    {
      "id": "d2-na-yoko-oh-no",
      "artist": "Yoko? Oh No!",
      "stage": null,
      "festivalDay": 2,
      "start": null,
      "end": null,
      "appleMusicPlaylist": null,
      "appleMusicArtistId": null,
      "musicBrainzId": null,
      "spotifyArtistId": null,
      "deezerArtistId": null,
      "instagramHandle": null
    },
    {
      "id": "d2-na-l-envoutante",
      "artist": "L'Envoûtante",
      "stage": null,
      "festivalDay": 2,
      "start": null,
      "end": null,
      "appleMusicPlaylist": null,
      "appleMusicArtistId": null,
      "musicBrainzId": null,
      "spotifyArtistId": null,
      "deezerArtistId": null,
      "instagramHandle": null
    },
    {
      "id": "d2-na-emmafleurs",
      "artist": "EmmaFleurs",
      "stage": null,
      "festivalDay": 2,
      "start": null,
      "end": null,
      "appleMusicPlaylist": null,
      "appleMusicArtistId": null,
      "musicBrainzId": null,
      "spotifyArtistId": null,
      "deezerArtistId": null,
      "instagramHandle": null
    },
    {
      "id": "d2-na-l-hkleon",
      "artist": "L'HKLéon",
      "stage": null,
      "festivalDay": 2,
      "start": null,
      "end": null,
      "appleMusicPlaylist": null,
      "appleMusicArtistId": null,
      "musicBrainzId": null,
      "spotifyArtistId": null,
      "deezerArtistId": null,
      "instagramHandle": null
    },
    {
      "id": "d2-na-ibhamuza",
      "artist": "Ibhamuza",
      "stage": null,
      "festivalDay": 2,
      "start": null,
      "end": null,
      "appleMusicPlaylist": null,
      "appleMusicArtistId": null,
      "musicBrainzId": null,
      "spotifyArtistId": null,
      "deezerArtistId": null,
      "instagramHandle": null
    },
    {
      "id": "d2-na-linoa",
      "artist": "Linoa",
      "stage": null,
      "festivalDay": 2,
      "start": null,
      "end": null,
      "appleMusicPlaylist": null,
      "appleMusicArtistId": null,
      "musicBrainzId": null,
      "spotifyArtistId": null,
      "deezerArtistId": null,
      "instagramHandle": null
    },
    {
      "id": "d2-na-dab-rozer",
      "artist": "Dab Rozer",
      "stage": null,
      "festivalDay": 2,
      "start": null,
      "end": null,
      "appleMusicPlaylist": null,
      "appleMusicArtistId": null,
      "musicBrainzId": null,
      "spotifyArtistId": null,
      "deezerArtistId": null,
      "instagramHandle": null
    },
    {
      "id": "d3-na-gaetan-roussel",
      "artist": "Gaëtan Roussel",
      "stage": null,
      "festivalDay": 3,
      "start": null,
      "end": null,
      "appleMusicPlaylist": null,
      "appleMusicArtistId": null,
      "musicBrainzId": null,
      "spotifyArtistId": null,
      "deezerArtistId": null,
      "instagramHandle": null,
      "description": "Gaëtan Roussel, né le 13 octobre 1972 à Rodez (Aveyron), est un auteur-compositeur-interprète et animateur de radio français."
    },
    {
      "id": "d3-na-helena",
      "artist": "Helena",
      "stage": null,
      "festivalDay": 3,
      "start": null,
      "end": null,
      "appleMusicPlaylist": null,
      "appleMusicArtistId": null,
      "musicBrainzId": null,
      "spotifyArtistId": null,
      "deezerArtistId": null,
      "instagramHandle": null
    },
    {
      "id": "d3-na-biga-ranx",
      "artist": "Biga*Ranx",
      "stage": null,
      "festivalDay": 3,
      "start": null,
      "end": null,
      "appleMusicPlaylist": null,
      "appleMusicArtistId": null,
      "musicBrainzId": null,
      "spotifyArtistId": null,
      "deezerArtistId": null,
      "instagramHandle": null,
      "description": "Biga*Ranx, de son vrai nom Gabriel Piotrowski, né le 27 septembre 1988 à Tours, est un chanteur, MC, producteur et artiste peintre qui se fait connaître au sein de la scène rap raggamuffin francophone au début des…"
    },
    {
      "id": "d3-na-deluxe",
      "artist": "Deluxe",
      "stage": null,
      "festivalDay": 3,
      "start": null,
      "end": null,
      "appleMusicPlaylist": null,
      "appleMusicArtistId": null,
      "musicBrainzId": null,
      "spotifyArtistId": null,
      "deezerArtistId": null,
      "instagramHandle": null,
      "description": "Deluxe est un groupe français d'electropop, originaire d'Aix-en-Provence, dans les Bouches-du-Rhône. Leur style musical possède des accents hip-hop, soul, funk, jazz et de groove."
    },
    {
      "id": "d3-na-perceval",
      "artist": "Perceval",
      "stage": null,
      "festivalDay": 3,
      "start": null,
      "end": null,
      "appleMusicPlaylist": null,
      "appleMusicArtistId": null,
      "musicBrainzId": null,
      "spotifyArtistId": null,
      "deezerArtistId": null,
      "instagramHandle": null,
      "description": "Perceval est dans la légende arthurienne un des chevaliers de la Table ronde. Dans la littérature galloise, son nom est Peredur. Il est surtout connu pour sa participation à la quête du Saint-Graal."
    },
    {
      "id": "d3-na-the-locos-ex-ska-p",
      "artist": "The Locos (ex Ska-P)",
      "stage": null,
      "festivalDay": 3,
      "start": null,
      "end": null,
      "appleMusicPlaylist": null,
      "appleMusicArtistId": null,
      "musicBrainzId": null,
      "spotifyArtistId": null,
      "deezerArtistId": null,
      "instagramHandle": null
    },
    {
      "id": "d3-na-keziah-jones",
      "artist": "Keziah Jones",
      "stage": null,
      "festivalDay": 3,
      "start": null,
      "end": null,
      "appleMusicPlaylist": null,
      "appleMusicArtistId": null,
      "musicBrainzId": null,
      "spotifyArtistId": null,
      "deezerArtistId": null,
      "instagramHandle": null,
      "description": "Keziah Jones, né Olufemi Sanyaolu à Lagos au Nigeria le 10 janvier 1968, est un chanteur, compositeur et guitariste nigérian. Il mêle le blues et le funk pour créer un style propre : le blufunk."
    },
    {
      "id": "d3-na-danakil",
      "artist": "Danakil",
      "stage": null,
      "festivalDay": 3,
      "start": null,
      "end": null,
      "appleMusicPlaylist": null,
      "appleMusicArtistId": null,
      "musicBrainzId": null,
      "spotifyArtistId": null,
      "deezerArtistId": null,
      "instagramHandle": null
    },
    {
      "id": "d3-na-solann",
      "artist": "Solann",
      "stage": null,
      "festivalDay": 3,
      "start": null,
      "end": null,
      "appleMusicPlaylist": null,
      "appleMusicArtistId": null,
      "musicBrainzId": null,
      "spotifyArtistId": null,
      "deezerArtistId": null,
      "instagramHandle": null,
      "description": "Solann Lis-Amboyan dite Solann, née le 26 décembre 1999 à Paris, est une auteure-compositrice-interprète et musicienne française."
    },
    {
      "id": "d3-na-assassin",
      "artist": "Assassin",
      "stage": null,
      "festivalDay": 3,
      "start": null,
      "end": null,
      "appleMusicPlaylist": null,
      "appleMusicArtistId": null,
      "musicBrainzId": null,
      "spotifyArtistId": null,
      "deezerArtistId": null,
      "instagramHandle": null
    },
    {
      "id": "d3-na-teddybear",
      "artist": "Teddybear",
      "stage": null,
      "festivalDay": 3,
      "start": null,
      "end": null,
      "appleMusicPlaylist": null,
      "appleMusicArtistId": null,
      "musicBrainzId": null,
      "spotifyArtistId": null,
      "deezerArtistId": null,
      "instagramHandle": null
    },
    {
      "id": "d3-na-mister-gang",
      "artist": "Mister Gang",
      "stage": null,
      "festivalDay": 3,
      "start": null,
      "end": null,
      "appleMusicPlaylist": null,
      "appleMusicArtistId": null,
      "musicBrainzId": null,
      "spotifyArtistId": null,
      "deezerArtistId": null,
      "instagramHandle": null,
      "description": "Mister Gang est un groupe de reggae français."
    },
    {
      "id": "d3-na-hk",
      "artist": "HK",
      "stage": null,
      "festivalDay": 3,
      "start": null,
      "end": null,
      "appleMusicPlaylist": null,
      "appleMusicArtistId": null,
      "musicBrainzId": null,
      "spotifyArtistId": null,
      "deezerArtistId": null,
      "instagramHandle": null
    },
    {
      "id": "d3-na-2l",
      "artist": "2L",
      "stage": null,
      "festivalDay": 3,
      "start": null,
      "end": null,
      "appleMusicPlaylist": null,
      "appleMusicArtistId": null,
      "musicBrainzId": null,
      "spotifyArtistId": null,
      "deezerArtistId": null,
      "instagramHandle": null
    },
    {
      "id": "d3-na-copycat",
      "artist": "Copycat",
      "stage": null,
      "festivalDay": 3,
      "start": null,
      "end": null,
      "appleMusicPlaylist": null,
      "appleMusicArtistId": null,
      "musicBrainzId": null,
      "spotifyArtistId": null,
      "deezerArtistId": null,
      "instagramHandle": null
    },
    {
      "id": "d3-na-bold-feat-youthstar",
      "artist": "Bold feat. Youthstar",
      "stage": null,
      "festivalDay": 3,
      "start": null,
      "end": null,
      "appleMusicPlaylist": null,
      "appleMusicArtistId": null,
      "musicBrainzId": null,
      "spotifyArtistId": null,
      "deezerArtistId": null,
      "instagramHandle": null
    },
    {
      "id": "d3-na-fatbabs-cheeko-davojah",
      "artist": "Fatbabs + Cheeko & Davojah",
      "stage": null,
      "festivalDay": 3,
      "start": null,
      "end": null,
      "appleMusicPlaylist": null,
      "appleMusicArtistId": null,
      "musicBrainzId": null,
      "spotifyArtistId": null,
      "deezerArtistId": null,
      "instagramHandle": null
    },
    {
      "id": "d3-na-b-low",
      "artist": "B-Low",
      "stage": null,
      "festivalDay": 3,
      "start": null,
      "end": null,
      "appleMusicPlaylist": null,
      "appleMusicArtistId": null,
      "musicBrainzId": null,
      "spotifyArtistId": null,
      "deezerArtistId": null,
      "instagramHandle": null
    },
    {
      "id": "d3-na-carte-blanche-a-radio-mdm",
      "artist": "Carte Blanche à Radio MDM",
      "stage": null,
      "festivalDay": 3,
      "start": null,
      "end": null,
      "appleMusicPlaylist": null,
      "appleMusicArtistId": null,
      "musicBrainzId": null,
      "spotifyArtistId": null,
      "deezerArtistId": null,
      "instagramHandle": null
    },
    {
      "id": "d3-na-minimum-fanfare",
      "artist": "Minimum Fanfare",
      "stage": null,
      "festivalDay": 3,
      "start": null,
      "end": null,
      "appleMusicPlaylist": null,
      "appleMusicArtistId": null,
      "musicBrainzId": null,
      "spotifyArtistId": null,
      "deezerArtistId": null,
      "instagramHandle": null
    },
    {
      "id": "d3-na-caus-rue",
      "artist": "Caus'Rue",
      "stage": null,
      "festivalDay": 3,
      "start": null,
      "end": null,
      "appleMusicPlaylist": null,
      "appleMusicArtistId": null,
      "musicBrainzId": null,
      "spotifyArtistId": null,
      "deezerArtistId": null,
      "instagramHandle": null
    }
  ]
}